package_image_process/__init__.py
package_image_process/processing/__init__.py
package_image_process/processing/combination.py
package_image_process/processing/transformation.py
package_image_process/utils/__init__.py
package_image_process/utils/io.py
package_image_process/utils/plot.py
package_image_process-0.0.1.dist-info/METADATA
package_image_process-0.0.1.dist-info/WHEEL
package_image_process-0.0.1.dist-info/top_level.txt
package_image_process-0.0.1.dist-info/RECORD
