Metadata-Version: 2.1
Name: package-image-process
Version: 0.0.1
Summary: Package Python to edit images
Home-page: https://github.com/GusMazzinghyDev
Author: gusmazzinghy
Author-email: gusmazzinghy@gmail.com
License: UNKNOWN
Platform: UNKNOWN
Requires-Python: >=3.8
Requires-Dist: matplotlib
Requires-Dist: numpy
Requires-Dist: scikit-image (>=0.16.1)
